bnb/__init__.py
bnb/assets/footer.html
bnb/assets/header.html
bnb/assets/sidebar.html
bnb/blogger.py
bnb/config.py
bnb/converter.py
bnb/exceptions.py
bnb/extractor.py
bnb/scanner.py
bnb/wrapper.py
bnb/writer.py
bnb-0.2.0.dist-info/entry_points.txt
bnb-0.2.0.dist-info/LICENSE
bnb-0.2.0.dist-info/WHEEL
bnb-0.2.0.dist-info/METADATA
bnb-0.2.0.dist-info/RECORD
