Metadata-Version: 2.1
Name: bnb
Version: 0.2.0
Summary: 
Author: Bram Vereertbrugghen
Author-email: bram@adimian.com
Requires-Python: >=3.8,<4.0
Classifier: Programming Language :: Python :: 3
Classifier: Programming Language :: Python :: 3.8
Requires-Dist: attr (>=0.3.1,<0.4.0)
Requires-Dist: click (>=7.1.2,<8.0.0)
Requires-Dist: markdown (>=3.3.3,<4.0.0)
Requires-Dist: pyyaml (>=5.3.1,<6.0.0)
Requires-Dist: questionary (>=1.5.2,<2.0.0)
Requires-Dist: smart_getenv (>=1.1.0,<2.0.0)
